main.py
mseep_mcpcrashcourse-0.1.5.dist-info/licenses/LICENSE
mseep_mcpcrashcourse-0.1.5.dist-info/METADATA
mseep_mcpcrashcourse-0.1.5.dist-info/WHEEL
mseep_mcpcrashcourse-0.1.5.dist-info/entry_points.txt
mseep_mcpcrashcourse-0.1.5.dist-info/top_level.txt
mseep_mcpcrashcourse-0.1.5.dist-info/RECORD
